LICENSE
MANIFEST.in
NOTICE
README.rst
setup.py
CleanerVersion_anfema.egg-info/PKG-INFO
CleanerVersion_anfema.egg-info/SOURCES.txt
CleanerVersion_anfema.egg-info/dependency_links.txt
CleanerVersion_anfema.egg-info/requires.txt
CleanerVersion_anfema.egg-info/top_level.txt
versions/__init__.py
versions/admin.py
versions/deletion.py
versions/exceptions.py
versions/models.py
versions/settings.py
versions/static/js/admin_addon.js
versions/templates/versions/datetimefilter.html
versions/util/__init__.py
versions/util/helper.py
versions/util/postgresql.py
versions_tests/__init__.py
versions_tests/admin.py
versions_tests/apps.py
versions_tests/models.py
versions_tests/urls.py
versions_tests/tests/__init__.py
versions_tests/tests/test_commands.py
versions_tests/tests/test_models.py
versions_tests/tests/test_utils.py